shadowScanner/__init__.py
shadowScanner/globals.py
shadowScanner/helpers.py
shadowScanner/main.py
shadowScanner/validation.py
shadowscanner-1.0.1.dist-info/METADATA
shadowscanner-1.0.1.dist-info/WHEEL
shadowscanner-1.0.1.dist-info/entry_points.txt
shadowscanner-1.0.1.dist-info/top_level.txt
shadowscanner-1.0.1.dist-info/RECORD
