Metadata-Version: 2.4
Name: shadowscanner
Version: 1.0.1
Summary: A scanner for Bug Bounty programs
Author: ISMAILSHADOW
License-Expression: MIT
Project-URL: Homepage, https://github.com/ISMAILSHADOW/shadowscanner
Requires-Python: >=3.8
Requires-Dist: requests
Requires-Dist: tqdm
Requires-Dist: urllib3
